README.md
setup.cfg
setup.py
vhost/__init__.py
vhost/__main__.py
vhost/action.py
vhost.egg-info/PKG-INFO
vhost.egg-info/SOURCES.txt
vhost.egg-info/dependency_links.txt
vhost.egg-info/entry_points.txt
vhost.egg-info/top_level.txt