Metadata-Version: 1.2
Name: vhost
Version: 0.1.1
Summary: Tool for help creating virtual hosts
Home-page: https://www.github.com/felipebool/vhost
Author: Felipe Lopes
Author-email: bolzin@gmail.com
License: MIT
Download-URL: https://www.github.com/felipebool/vhost/archive/0.1.1.tar.gz
Platform: UNKNOWN
Requires-Python: >=3
